crucio/ADASYN.py
crucio/ICOTE.py
crucio/MTDF.py
crucio/MWMOTE.py
crucio/SCUT.py
crucio/SLS.py
crucio/SMOTE.py
crucio/SMOTEENN.py
crucio/SMOTENC.py
crucio/SMOTETOMEK.py
crucio/TKRKNN.py
crucio/__init__.py
crucio/erorrs.py
crucio-0.1.94.dist-info/LICENSE.txt
crucio-0.1.94.dist-info/METADATA
crucio-0.1.94.dist-info/WHEEL
crucio-0.1.94.dist-info/top_level.txt
crucio-0.1.94.dist-info/RECORD
