Metadata-Version: 2.1
Name: crucio
Version: 0.1.94
Summary: Crucio is a python sci-kit learn inspired package for class imbalance. It use some classic methods for class balancing taking as parameters a data frame and the target column.
Home-page: https://github.com/SigmoidAI/crucio
Author: Păpăluță Vasile, Stojoc Vladimir
Author-email: vladimir.stojoc@gmail.com
License: MIT
Download-URL: https://github.com/ScienceKot/crucio/archive/v1.0.tar.gz
Keywords: ml,machine learning,imbalanced learning,class balancing,python
Platform: UNKNOWN
Classifier: Development Status :: 3 - Alpha
Classifier: Framework :: Jupyter
Classifier: Intended Audience :: Science/Research
Classifier: Topic :: Scientific/Engineering :: Artificial Intelligence
Classifier: Topic :: Scientific/Engineering :: Mathematics
Classifier: Topic :: Software Development :: Libraries :: Python Modules
Classifier: Topic :: Software Development :: Build Tools
Classifier: License :: OSI Approved :: MIT License
Classifier: Programming Language :: Python :: 3
Classifier: Programming Language :: Python :: 3.4
Classifier: Programming Language :: Python :: 3.5
Classifier: Programming Language :: Python :: 3.6
Classifier: Programming Language :: Python :: 3.7
Classifier: Programming Language :: Python :: 3.8
License-File: LICENSE.txt
Requires-Dist: numpy
Requires-Dist: pandas
Requires-Dist: scikit-learn
Requires-Dist: statistics
Requires-Dist: numba
